netskope_api/__init__.py
netskope_api/iterator/__init__.py
netskope_api/iterator/const.py
netskope_api/iterator/netskope_iterator.py
netskope_api/iterator/netskope_iterator_client.py
netskope_api/iterator/operation.py
netskope_api/token_management/__init__.py
netskope_api/token_management/netskope_management.py
netskope_api/token_management/netskope_management_client.py
netskopesdk-0.0.41.dist-info/LICENSE
netskopesdk-0.0.41.dist-info/METADATA
netskopesdk-0.0.41.dist-info/WHEEL
netskopesdk-0.0.41.dist-info/top_level.txt
netskopesdk-0.0.41.dist-info/RECORD
