Metadata-Version: 2.1
Name: netskopesdk
Version: 0.0.41
Summary: SDK to download the Netskope Events
Home-page: http://www.netskope.com/
Author: Bharath Rajendran
Author-email: bharath@netskope.com
Project-URL: Bug Tracker, http://www.netskope.com/
Classifier: Programming Language :: Python :: 3
Classifier: Operating System :: OS Independent
Requires-Python: >=3.6
License-File: LICENSE
Requires-Dist: requests >=2.27.1
